parsomics_plugin_proteinfer/__init__.py
parsomics_plugin_proteinfer/annotation_type.py
parsomics_plugin_proteinfer/file_factory.py
parsomics_plugin_proteinfer/parser.py
parsomics_plugin_proteinfer/plugin_initializer.py
parsomics_plugin_proteinfer/populate.py
parsomics_plugin_proteinfer/processor.py
parsomics_plugin_proteinfer/validated_file.py
parsomics_plugin_proteinfer-0.1.4.dist-info/LICENSE
parsomics_plugin_proteinfer-0.1.4.dist-info/METADATA
parsomics_plugin_proteinfer-0.1.4.dist-info/WHEEL
parsomics_plugin_proteinfer-0.1.4.dist-info/RECORD
